vascular_encoding_framework/__init__.py
vascular_encoding_framework/_base/__init__.py
vascular_encoding_framework/_base/encoding.py
vascular_encoding_framework/_base/encoding_tree.py
vascular_encoding_framework/_base/misc.py
vascular_encoding_framework/_base/node.py
vascular_encoding_framework/_base/spatial_object.py
vascular_encoding_framework/_base/spline.py
vascular_encoding_framework/_base/tree.py
vascular_encoding_framework/_base/value_typed_dict.py
vascular_encoding_framework/alignment/__init__.py
vascular_encoding_framework/alignment/alignment.py
vascular_encoding_framework/alignment/gpa.py
vascular_encoding_framework/centerline/__init__.py
vascular_encoding_framework/centerline/centerline.py
vascular_encoding_framework/centerline/centerline_tree.py
vascular_encoding_framework/centerline/curve.py
vascular_encoding_framework/centerline/domain_extractors.py
vascular_encoding_framework/centerline/parallel_transport.py
vascular_encoding_framework/centerline/path_extractor.py
vascular_encoding_framework/encoding/__init__.py
vascular_encoding_framework/encoding/radius.py
vascular_encoding_framework/encoding/remesh/__init__.py
vascular_encoding_framework/encoding/remesh/cross_sections.py
vascular_encoding_framework/encoding/remesh/remesh.py
vascular_encoding_framework/encoding/vascular_encoding.py
vascular_encoding_framework/encoding/vessel_encoding.py
vascular_encoding_framework/messages.py
vascular_encoding_framework/splines/__init__.py
vascular_encoding_framework/splines/bivariate.py
vascular_encoding_framework/splines/psplines.py
vascular_encoding_framework/splines/splines.py
vascular_encoding_framework/splines/univariate.py
vascular_encoding_framework/utils/__init__.py
vascular_encoding_framework/utils/_io.py
vascular_encoding_framework/utils/geometry.py
vascular_encoding_framework/utils/spatial.py
vascular_encoding_framework/vascular_mesh/__init__.py
vascular_encoding_framework/vascular_mesh/boundaries.py
vascular_encoding_framework-0.0.2.dist-info/METADATA
vascular_encoding_framework-0.0.2.dist-info/WHEEL
vascular_encoding_framework-0.0.2.dist-info/RECORD
