Metadata-Version: 2.3
Name: vascular-encoding-framework
Version: 0.0.2
Summary: Python package with the Vascular Encoding Framework implementation
Author: Pau Romero
Author-email: paurodea@gmail.com
Requires-Python: >=3.9
Classifier: Programming Language :: Python :: 3
Classifier: Programming Language :: Python :: 3.9
Classifier: Programming Language :: Python :: 3.10
Classifier: Programming Language :: Python :: 3.11
Classifier: Programming Language :: Python :: 3.12
Classifier: Programming Language :: Python :: 3.13
Requires-Dist: pyvista (>=0.44.2,<0.45.0)
Requires-Dist: scikit-learn (>=1.6.1,<2.0.0)
